{
  "contract": "BSS Frontend v1.0.0 to Backend API v1",
  "readiness": "FULL_PASS",
  "contractReviewedAt": "2026-07-13",
  "frontendBaseline": "91323c7cdbbbbf7b965c4926c94a11af6d31bf62",
  "repositoryBaseline": "e35b53af848b855c986e467a6efacdea4dde777e",
  "openapi": {
    "file": "openapi/bss-mvp-api-v1.yaml",
    "sha256": "bbb284ffcb934ff087e967c9d6cd4ad27c66108b5c7876c1598545c6d269d5c7",
    "version": "1.0.0",
    "status": "FULL_PASS_APPROVED",
    "paths": 40,
    "operations": 51,
    "phaseAImplementedOperations": 30
  },
  "statusLegend": {
    "covered": "Approved OpenAPI v1 contains the required operation and authoritative server semantics.",
    "excluded": "Demo-only or separately proposed scope; it does not call the production v1 API."
  },
  "screens": [
    {
      "id": "home",
      "status": "covered",
      "operations": ["getDashboardSummary"]
    },
    {
      "id": "attendance",
      "status": "covered",
      "operations": ["listAttendance", "listWorkers", "listShifts", "listDepartments"]
    },
    {
      "id": "mytime",
      "status": "covered",
      "operations": ["getWorkerAttendance", "createCorrectionRequest"]
    },
    {
      "id": "workers",
      "status": "covered",
      "operations": ["listWorkers", "createWorker", "updateWorker", "listDepartments", "listShifts", "listWorkerRfidCards", "assignWorkerRfidCard", "blockRfidCard"]
    },
    {
      "id": "worker",
      "status": "covered",
      "operations": ["getWorker", "getWorkerAttendance", "listLeaveRequests", "listLeaveBalances", "listWorkerRfidCards", "assignWorkerRfidCard", "blockRfidCard"]
    },
    {
      "id": "shifts",
      "status": "covered",
      "operations": ["listShifts", "createShift", "updateShift"]
    },
    {
      "id": "requests",
      "status": "covered",
      "operations": ["listLeaveRequests", "createLeaveRequest", "listLeaveBalances", "approveLeaveRequest", "rejectLeaveRequest", "cancelOwnLeaveRequest"]
    },
    {
      "id": "vacations",
      "status": "covered",
      "operations": ["listLeaveRequests", "listLeaveBalances", "listHolidays"]
    },
    {
      "id": "sharedLeave",
      "status": "excluded",
      "operations": [],
      "note": "Frontend demonstration and separately proposed MVP Scope v1.1 only."
    },
    {
      "id": "corrections",
      "status": "covered",
      "operations": ["listCorrectionRequests", "createCorrectionRequest", "approveCorrectionRequest", "rejectCorrectionRequest", "cancelOwnCorrectionRequest"]
    },
    {
      "id": "reports",
      "status": "covered",
      "operations": ["createReportPreview", "listReportExports", "createReportExport", "getReportExport"]
    },
    {
      "id": "terminal",
      "status": "covered",
      "operations": ["listTerminals", "pairTerminal", "revokeTerminal", "listTerminalSyncEvents", "ingestTerminalEventBatch", "terminalHeartbeat"]
    },
    {
      "id": "terminalDemo",
      "status": "excluded",
      "operations": [],
      "note": "Local simulator never writes production attendance or audit data."
    },
    {
      "id": "flow",
      "status": "excluded",
      "operations": [],
      "note": "Static sales/demo content."
    },
    {
      "id": "roles",
      "status": "covered",
      "operations": ["listUsers", "inviteUser", "acceptInvitation", "updateUser"]
    },
    {
      "id": "audit",
      "status": "covered",
      "operations": ["listAuditEvents"]
    },
    {
      "id": "settings",
      "status": "covered",
      "operations": ["getOrganization", "updateOrganization", "listDepartments", "createDepartment", "updateDepartment", "listHolidays", "replaceHolidaysForYear"]
    }
  ],
  "contractGatesBeforeLaterPhases": []
}
